ddc/__init__.py
ddc/cli.py
ddc/info.py
ddc/meta_utils.py
ddc/task_black.py
ddc/task_build_assets.py
ddc/task_build_docker_image.py
ddc/task_grpc_docs.py
ddc/task_lint.py
ddc/task_meta.py
ddc/task_test.py
ddc/utils.py
ddc-0.3.17.dist-info/LICENSE
ddc-0.3.17.dist-info/METADATA
ddc-0.3.17.dist-info/WHEEL
ddc-0.3.17.dist-info/entry_points.txt
ddc-0.3.17.dist-info/top_level.txt
ddc-0.3.17.dist-info/RECORD
